{"stats":{"minecraft:killed_by":{"minecraft:zombie":1,"minecraft:iron_golem":1,"minecraft:skeleton":1},"minecraft:broken":{"minecraft:iron_shovel":10,"minecraft:stone_pickaxe":1,"minecraft:stone_axe":1,"minecraft:iron_sword":1,"minecraft:stone_shovel":2,"minecraft:iron_hoe":2,"minecraft:stone_hoe":1,"minecraft:iron_axe":2,"minecraft:iron_pickaxe":8},"minecraft:killed":{"minecraft:zombified_piglin":1,"minecraft:spider":3,"minecraft:skeleton":11,"minecraft:salmon":9,"minecraft:iron_golem":7,"minecraft:creeper":2,"minecraft:sheep":1,"minecraft:zombie":10,"minecraft:glow_squid":1,"minecraft:cow":43,"minecraft:phantom":1,"minecraft:wandering_trader":1,"minecraft:villager":2},"minecraft:used":{"minecraft:iron_shovel":2550,"minecraft:spruce_slab":271,"minecraft:ladder":15,"minecraft:poppy":1,"minecraft:chest":85,"minecraft:iron_sword":291,"minecraft:bell":4,"minecraft:carrot":698,"minecraft:furnace_minecart":1,"minecraft:tuff":8,"minecraft:azure_bluet":1,"minecraft:glass":61,"minecraft:lava_bucket":20,"minecraft:lantern":12,"minecraft:repeater":8,"minecraft:red_carpet":4,"minecraft:oak_sapling":41,"minecraft:furnace":7,"minecraft:beetroot_seeds":16,"minecraft:egg":9,"minecraft:potato":109,"minecraft:diorite":1,"minecraft:dropper":1,"minecraft:stone_pickaxe":242,"minecraft:powered_rail":2,"minecraft:oak_planks":21,"minecraft:wooden_pickaxe":10,"minecraft:composter":15,"minecraft:sugar_cane":177,"minecraft:blue_bed":12,"minecraft:blast_furnace":9,"minecraft:dripstone_block":21,"minecraft:redstone_torch":12,"minecraft:bread":79,"minecraft:lectern":13,"minecraft:gravel":1,"minecraft:smithing_table":5,"minecraft:andesite":6,"minecraft:bone_meal":1,"minecraft:oak_fence":254,"minecraft:stone_sword":64,"minecraft:flint_and_steel":3,"minecraft:stone_shovel":265,"minecraft:redstone":109,"minecraft:light_gray_carpet":4,"minecraft:spruce_planks":6,"minecraft:stone_hoe":146,"minecraft:netherrack":338,"minecraft:orange_bed":9,"minecraft:torch":843,"minecraft:brewing_stand":4,"minecraft:dirt":1874,"minecraft:anvil":1,"minecraft:hopper":28,"minecraft:yellow_carpet":4,"minecraft:granite":9,"minecraft:iron_hoe":500,"minecraft:bookshelf":11,"minecraft:iron_axe":1040,"minecraft:oak_stairs":18,"minecraft:spruce_button":2,"minecraft:minecart":2,"minecraft:cooked_beef":32,"minecraft:cobbled_deepslate":71,"minecraft:pointed_dripstone":12,"minecraft:wheat_seeds":791,"minecraft:cooked_mutton":3,"minecraft:water_bucket":90,"minecraft:glass_bottle":3,"minecraft:blue_wool":4,"minecraft:cauldron":24,"minecraft:cobblestone_slab":10,"minecraft:stonecutter":5,"minecraft:rail":73,"minecraft:comparator":1,"minecraft:oak_slab":28,"minecraft:crafting_table":8,"minecraft:white_bed":25,"minecraft:spruce_log":1,"minecraft:smoker":3,"minecraft:oak_log":4,"minecraft:piston":39,"minecraft:wooden_hoe":84,"minecraft:apple":2,"minecraft:iron_pickaxe":2045,"minecraft:spruce_sapling":33,"minecraft:stone_axe":138,"minecraft:blue_carpet":6,"minecraft:cobblestone":300,"minecraft:potion":1,"minecraft:bucket":153,"minecraft:yellow_bed":19,"minecraft:dandelion":7},"minecraft:crafted":{"minecraft:oak_planks":820,"minecraft:orange_carpet":3,"minecraft:bookshelf":13,"minecraft:glass":72,"minecraft:hopper":26,"minecraft:repeater":5,"minecraft:iron_boots":2,"minecraft:comparator":1,"minecraft:chest":90,"minecraft:stone_hoe":1,"minecraft:oak_fence":201,"minecraft:name_tag":2,"minecraft:raw_iron_block":14,"minecraft:smoker":2,"minecraft:glass_bottle":6,"minecraft:dropper":1,"minecraft:oak_slab":36,"minecraft:emerald":84,"minecraft:cauldron":12,"minecraft:crafting_table":2,"minecraft:spruce_planks":812,"minecraft:wooden_pickaxe":1,"minecraft:iron_helmet":1,"minecraft:raw_gold_block":1,"minecraft:golden_leggings":1,"minecraft:lectern":2,"minecraft:diamond_pickaxe":1,"minecraft:iron_chestplate":1,"minecraft:book":41,"minecraft:wooden_hoe":2,"minecraft:paper":1176,"minecraft:charcoal":7,"minecraft:yellow_dye":3,"minecraft:stick":808,"minecraft:iron_ingot":48,"minecraft:iron_pickaxe":9,"minecraft:stone_sword":1,"minecraft:light_gray_dye":2,"minecraft:redstone_torch":22,"minecraft:light_gray_carpet":9,"minecraft:shears":1,"minecraft:redstone":150,"minecraft:raw_iron":144,"minecraft:coal":162,"minecraft:stone_shovel":2,"minecraft:spruce_button":1,"minecraft:furnace":5,"minecraft:blast_furnace":1,"minecraft:piston":22,"minecraft:yellow_bed":5,"minecraft:flint_and_steel":1,"minecraft:lantern":12,"minecraft:iron_axe":7,"minecraft:ladder":9,"minecraft:iron_hoe":2,"minecraft:spruce_slab":204,"minecraft:stone_pickaxe":4,"minecraft:redstone_block":17,"minecraft:wheat":234,"minecraft:coal_block":18,"minecraft:red_dye":5,"minecraft:yellow_carpet":9,"minecraft:iron_sword":2,"minecraft:blue_bed":5,"minecraft:bucket":23,"minecraft:red_carpet":9,"minecraft:stone_axe":1,"minecraft:orange_dye":2,"minecraft:bread":161,"minecraft:air":0,"minecraft:blue_dye":2,"minecraft:raw_gold":9,"minecraft:iron_shovel":12,"minecraft:iron_leggings":1,"minecraft:white_bed":1,"minecraft:torch":820,"minecraft:orange_bed":5,"minecraft:lapis_lazuli":9,"minecraft:lapis_block":4,"minecraft:blue_carpet":12},"minecraft:dropped":{"minecraft:lapis_lazuli":2,"minecraft:rail":2,"minecraft:flint":2,"minecraft:cobblestone_stairs":3,"minecraft:dirt":124,"minecraft:cornflower":3,"minecraft:gold_nugget":1,"minecraft:iron_pickaxe":1,"minecraft:bone":1,"minecraft:gravel":7,"minecraft:sugar_cane":1,"minecraft:cobbled_deepslate":36,"minecraft:rotten_flesh":8,"minecraft:oak_planks":24,"minecraft:azure_bluet":1,"minecraft:white_bed":1,"minecraft:salmon":10,"minecraft:carrot":52,"minecraft:poppy":65,"minecraft:oak_fence_gate":1,"minecraft:deepslate_tiles":1,"minecraft:gunpowder":1,"minecraft:spruce_slab":2,"minecraft:arrow":6,"minecraft:netherrack":15,"minecraft:water_bucket":1,"minecraft:iron_ingot":39,"minecraft:bread":63,"minecraft:wheat_seeds":38,"minecraft:mossy_cobblestone":8,"minecraft:smithing_table":1,"minecraft:oak_fence":53,"minecraft:cobblestone":1,"minecraft:granite":24,"minecraft:stick":13,"minecraft:oxeye_daisy":2,"minecraft:diorite":5,"minecraft:wooden_hoe":1,"minecraft:torch":14,"minecraft:oak_stairs":36,"minecraft:iron_shovel":1,"minecraft:paper":34,"minecraft:string":1,"minecraft:dandelion":9,"minecraft:oak_trapdoor":6,"minecraft:raw_copper":2,"minecraft:tuff":4,"minecraft:clay_ball":32,"minecraft:name_tag":2,"minecraft:spruce_fence":2,"minecraft:cobblestone_slab":7,"minecraft:diamond_pickaxe":1,"minecraft:andesite":16,"minecraft:spruce_log":3},"minecraft:picked_up":{"minecraft:iron_chestplate":2,"minecraft:wheat":666,"minecraft:anvil":1,"minecraft:yellow_wool":28,"minecraft:smithing_table":6,"minecraft:lead":2,"minecraft:oak_stairs":289,"minecraft:brewing_stand":4,"minecraft:string":5,"minecraft:raw_copper":7,"minecraft:iron_leggings":2,"minecraft:beetroot":17,"minecraft:deepslate_tiles":1,"minecraft:gold_nugget":9,"minecraft:cobbled_deepslate":144,"minecraft:bucket":5,"minecraft:spruce_planks":108,"minecraft:cobblestone_slab":17,"minecraft:redstone_torch":11,"minecraft:iron_pickaxe":5,"minecraft:furnace":6,"minecraft:iron_boots":2,"minecraft:blue_wool":54,"minecraft:stick":58,"minecraft:composter":15,"minecraft:oak_fence":139,"minecraft:torch":240,"minecraft:pointed_dripstone":80,"minecraft:diorite":9,"minecraft:cauldron":12,"minecraft:orange_bed":4,"minecraft:rotten_flesh":24,"minecraft:honey_bottle":1,"minecraft:white_terracotta":47,"minecraft:cobblestone":844,"minecraft:furnace_minecart":1,"minecraft:cooked_beef":18,"minecraft:repeater":3,"minecraft:water_bucket":6,"minecraft:andesite":27,"minecraft:potato":242,"minecraft:flint":5,"minecraft:tuff":12,"minecraft:lapis_lazuli":43,"minecraft:dirt":3152,"minecraft:glass":70,"minecraft:bone":10,"minecraft:stonecutter":5,"minecraft:wheat_seeds":1912,"minecraft:raw_gold":59,"minecraft:bell":4,"minecraft:powered_rail":2,"minecraft:stone_hoe":1,"minecraft:oak_planks":288,"minecraft:sand":2,"minecraft:poisonous_potato":3,"minecraft:mossy_cobblestone":26,"minecraft:orange_wool":42,"minecraft:diamond":4,"minecraft:granite":37,"minecraft:bone_meal":7,"minecraft:spruce_button":1,"minecraft:emerald":67,"minecraft:bread":108,"minecraft:oak_sapling":58,"minecraft:netherrack":459,"minecraft:crimson_roots":3,"minecraft:diamond_pickaxe":1,"minecraft:charcoal":1,"minecraft:crafting_table":10,"minecraft:azure_bluet":2,"minecraft:ladder":6,"minecraft:clay_ball":48,"minecraft:wooden_pickaxe":1,"minecraft:cornflower":7,"minecraft:oak_trapdoor":6,"minecraft:iron_axe":4,"minecraft:iron_shovel":4,"minecraft:beef":107,"minecraft:lectern":11,"minecraft:poppy":24,"minecraft:spruce_slab":87,"minecraft:light_gray_wool":30,"minecraft:minecart":3,"minecraft:sugar_cane":1116,"minecraft:chest":21,"minecraft:piston":19,"minecraft:egg":12,"minecraft:raw_iron":332,"minecraft:oak_door":2,"minecraft:spruce_fence":4,"minecraft:carrot":1432,"minecraft:redstone":225,"minecraft:blue_carpet":2,"minecraft:arrow":7,"minecraft:beetroot_seeds":52,"minecraft:shears":1,"minecraft:hay_block":2,"minecraft:mutton":1,"minecraft:white_wool":5,"minecraft:rail":75,"minecraft:oxeye_daisy":7,"minecraft:stripped_oak_log":16,"minecraft:glow_ink_sac":7,"minecraft:salmon":21,"minecraft:leather":48,"minecraft:oak_log":259,"minecraft:nether_wart_block":5,"minecraft:golden_boots":1,"minecraft:yellow_bed":14,"minecraft:gunpowder":1,"minecraft:cobblestone_stairs":8,"minecraft:wooden_hoe":2,"minecraft:blue_bed":7,"minecraft:paper":148,"minecraft:apple":2,"minecraft:stone_pickaxe":1,"minecraft:oak_fence_gate":2,"minecraft:iron_ingot":178,"minecraft:glass_bottle":5,"minecraft:iron_sword":4,"minecraft:book":2,"minecraft:red_wool":9,"minecraft:quartz":12,"minecraft:dandelion":43,"minecraft:raw_iron_block":2,"minecraft:dripstone_block":129,"minecraft:gravel":25,"minecraft:lava_bucket":12,"minecraft:spruce_sapling":33,"minecraft:blast_furnace":4,"minecraft:white_bed":26,"minecraft:spruce_log":219,"minecraft:spider_eye":1,"minecraft:iron_helmet":1,"minecraft:gray_wool":1,"minecraft:terracotta":2,"minecraft:coal":440,"minecraft:hopper":2},"minecraft:custom":{"minecraft:animals_bred":149,"minecraft:interact_with_crafting_table":189,"minecraft:bell_ring":3,"minecraft:leave_game":10,"minecraft:time_since_death":208219,"minecraft:sprint_one_cm":1577903,"minecraft:drop":120,"minecraft:talked_to_villager":110,"minecraft:play_time":655260,"minecraft:deaths":5,"minecraft:jump":10660,"minecraft:interact_with_brewingstand":1,"minecraft:walk_on_water_one_cm":134312,"minecraft:interact_with_furnace":54,"minecraft:traded_with_villager":128,"minecraft:sleep_in_bed":22,"minecraft:damage_dealt":19541,"minecraft:player_kills":1,"minecraft:crouch_one_cm":150287,"minecraft:interact_with_smoker":11,"minecraft:use_cauldron":45,"minecraft:inspect_dispenser":1,"minecraft:inspect_dropper":1,"minecraft:interact_with_anvil":1,"minecraft:mob_kills":93,"minecraft:inspect_hopper":62,"minecraft:fill_cauldron":4,"minecraft:climb_one_cm":30269,"minecraft:walk_one_cm":2109275,"minecraft:sneak_time":45233,"minecraft:walk_under_water_one_cm":45575,"minecraft:interact_with_blast_furnace":32,"minecraft:total_world_time":655260,"minecraft:interact_with_stonecutter":4,"minecraft:time_since_rest":78654,"minecraft:damage_taken":5401,"minecraft:swim_one_cm":59860,"minecraft:fly_one_cm":2234689,"minecraft:open_chest":512,"minecraft:fall_one_cm":236492},"minecraft:mined":{"minecraft:blue_carpet":2,"minecraft:spruce_planks":42,"minecraft:white_bed":25,"minecraft:oak_sapling":10,"minecraft:cobblestone_stairs":6,"minecraft:brewing_stand":4,"minecraft:granite":35,"minecraft:grass_block":1860,"minecraft:blue_wool":4,"minecraft:composter":15,"minecraft:hopper":2,"minecraft:oxeye_daisy":6,"minecraft:tall_seagrass":1,"minecraft:raw_iron_block":2,"minecraft:iron_ore":213,"minecraft:fire":1,"minecraft:cobbled_deepslate":6,"minecraft:anvil":1,"minecraft:deepslate_lapis_ore":2,"minecraft:azure_bluet":1,"minecraft:pointed_dripstone":13,"minecraft:dirt_path":61,"minecraft:oak_stairs":270,"minecraft:spruce_slab":78,"minecraft:orange_bed":4,"minecraft:deepslate_redstone_ore":23,"minecraft:crimson_nylium":32,"minecraft:smoker":1,"minecraft:clay":4,"minecraft:torch":28,"minecraft:blast_furnace":6,"minecraft:poppy":5,"minecraft:chest":25,"minecraft:nether_quartz_ore":12,"minecraft:glass":5,"minecraft:cobblestone":276,"minecraft:sugar_cane":583,"minecraft:oak_planks":142,"minecraft:wall_torch":14,"minecraft:cauldron":12,"minecraft:white_terracotta":47,"minecraft:repeater":3,"minecraft:powered_rail":1,"minecraft:nether_wart_block":5,"minecraft:wheat":690,"minecraft:grass":879,"minecraft:oak_log":230,"minecraft:beetroots":18,"minecraft:oak_fence_gate":3,"minecraft:sand":1,"minecraft:dirt":1027,"minecraft:stonecutter":5,"minecraft:netherrack":451,"minecraft:piston":19,"minecraft:oak_leaves":129,"minecraft:deepslate":113,"minecraft:nether_gold_ore":2,"minecraft:tuff":13,"minecraft:mossy_cobblestone":18,"minecraft:deepslate_diamond_ore":4,"minecraft:oak_door":2,"minecraft:ladder":1,"minecraft:spruce_fence":2,"minecraft:crimson_roots":1,"minecraft:redstone_wire":50,"minecraft:spruce_leaves":102,"minecraft:hay_block":2,"minecraft:redstone_ore":6,"minecraft:oak_trapdoor":2,"minecraft:spruce_sapling":7,"minecraft:furnace":7,"minecraft:carrots":412,"minecraft:andesite":17,"minecraft:bell":3,"minecraft:potatoes":82,"minecraft:cobblestone_slab":17,"minecraft:deepslate_iron_ore":43,"minecraft:rail":35,"minecraft:stripped_oak_log":16,"minecraft:stone":396,"minecraft:podzol":66,"minecraft:smithing_table":5,"minecraft:glass_pane":14,"minecraft:dandelion":21,"minecraft:oak_fence":89,"minecraft:crafting_table":7,"minecraft:cornflower":5,"minecraft:lectern":11,"minecraft:tall_grass":177,"minecraft:copper_ore":4,"minecraft:deepslate_coal_ore":3,"minecraft:lapis_ore":5,"minecraft:deepslate_gold_ore":24,"minecraft:diorite":8,"minecraft:blue_bed":7,"minecraft:redstone_torch":8,"minecraft:spruce_log":172,"minecraft:yellow_bed":14,"minecraft:coal_ore":269,"minecraft:gravel":34,"minecraft:dripstone_block":70,"minecraft:terracotta":2,"minecraft:gold_ore":15}},"DataVersion":3218}